fastci/__init__.py
fastci/application.py
fastci/utilities/__init__.py
fastci/utilities/annotations.py
fastci/utilities/constants.py
fastci/utilities/mqtt.py
fastci/utilities/parsing.py
fastci/utilities/type_aliases.py
fastci/utilities/type_definitions.py
fastci-1.0.0.dist-info/METADATA
fastci-1.0.0.dist-info/WHEEL
fastci-1.0.0.dist-info/top_level.txt
fastci-1.0.0.dist-info/RECORD
